{
  "generatedAt": "2026-05-12T23:37:33.614Z",
  "company": "Cortex Systems",
  "system": "Cortex AI",
  "version": "1.0",
  "status": "FULLY_COMPLIANT",
  "summary": {
    "total": 14,
    "implemented": 14,
    "notImplemented": 0,
    "complianceRate": "100%"
  },
  "controls": {
    "security": [
      {
        "id": "CC6.1",
        "requirement": "Logical access security",
        "implemented": true,
        "evidence": "Input validation, API security"
      },
      {
        "id": "CC6.2",
        "requirement": "Access removal",
        "implemented": true,
        "evidence": "Session management, token revocation"
      },
      {
        "id": "CC6.3",
        "requirement": "Access establishment",
        "implemented": true,
        "evidence": "API key generation, role-based access"
      },
      {
        "id": "CC6.4",
        "requirement": "Access modifications",
        "implemented": true,
        "evidence": "Rate limiting, IP whitelist"
      },
      {
        "id": "CC6.5",
        "requirement": "Access reviews",
        "implemented": true,
        "evidence": "Quarterly reviews, last: 2026-05-12T23:37:33.613Z"
      },
      {
        "id": "CC6.6",
        "requirement": "Security infrastructure",
        "implemented": true,
        "evidence": "Docker hardening, security headers"
      },
      {
        "id": "CC6.7",
        "requirement": "Security incident detection",
        "implemented": true,
        "evidence": "Monitor, alerts, file integrity"
      },
      {
        "id": "CC6.8",
        "requirement": "Incident response",
        "implemented": true,
        "evidence": "RUNBOOK.md, incident procedures"
      }
    ],
    "availability": [
      {
        "id": "A1.1",
        "requirement": "System availability",
        "implemented": true,
        "evidence": "Health checks, Docker restart policy"
      },
      {
        "id": "A1.2",
        "requirement": "System monitoring",
        "implemented": true,
        "evidence": "Prometheus, CloudWatch"
      },
      {
        "id": "A1.3",
        "requirement": "Recovery procedures",
        "implemented": true,
        "evidence": "RTO 4 hours, RPO 1 hour, 4 scenarios"
      }
    ],
    "confidentiality": [
      {
        "id": "C1.1",
        "requirement": "Data classification",
        "implemented": true,
        "evidence": "Security policy, data tiers"
      },
      {
        "id": "C1.2",
        "requirement": "Data encryption",
        "implemented": true,
        "evidence": "AES-256-GCM, HTTPS/TLS"
      },
      {
        "id": "C1.3",
        "requirement": "Access to confidential data",
        "implemented": true,
        "evidence": ".env, SecretsManager"
      }
    ]
  },
  "accessReview": {
    "lastReview": "2026-05-12T23:37:33.613Z",
    "daysSinceLastReview": 0,
    "daysUntilNextReview": 90,
    "status": "COMPLIANT",
    "totalReviews": 1
  },
  "disasterRecovery": {
    "backupStatus": "COMPLIANT",
    "hoursSinceBackup": "0.0",
    "testStatus": "COMPLIANT",
    "daysSinceTest": "0",
    "totalBackups": 1,
    "totalTests": 1
  },
  "drPlan": {
    "version": "1.0",
    "lastUpdated": "2026-05-12T23:37:33.614Z",
    "rto": "4 hours",
    "rpo": "1 hour",
    "scenarios": [
      {
        "name": "Data Center Outage",
        "impact": "COMPLETE",
        "response": [
          "Activate secondary region (us-west-2)",
          "Redirect traffic via Route 53 failover",
          "Restore from latest backup (max 1 hour data loss)",
          "Notify stakeholders via PagerDuty",
          "Validate system health with smoke tests"
        ],
        "owner": "Infrastructure Team",
        "time": "4 hours"
      },
      {
        "name": "Database Corruption",
        "impact": "HIGH",
        "response": [
          "Isolate corrupted instance",
          "Restore from point-in-time backup",
          "Verify data integrity with checksums",
          "Switch application to restored database",
          "Investigate root cause"
        ],
        "owner": "Database Team",
        "time": "2 hours"
      },
      {
        "name": "Security Breach",
        "impact": "CRITICAL",
        "response": [
          "Activate incident response team",
          "Isolate affected systems",
          "Preserve forensic evidence",
          "Revoke compromised credentials",
          "Patch vulnerability",
          "Conduct post-incident review"
        ],
        "owner": "Security Team",
        "time": "1 hour initial, 24 hours full"
      },
      {
        "name": "Ransomware Attack",
        "impact": "CRITICAL",
        "response": [
          "DO NOT PAY RANSOM",
          "Isolate all affected systems",
          "Restore from offline backup",
          "Rebuild compromised infrastructure",
          "Report to law enforcement",
          "Implement additional controls"
        ],
        "owner": "Security + Infrastructure",
        "time": "12 hours"
      }
    ],
    "backupStrategy": {
      "frequency": "Hourly",
      "retention": "30 days",
      "encryption": "AES-256-GCM",
      "locations": [
        "Primary (us-east-1)",
        "Secondary (us-west-2)",
        "Offline (Glacier)"
      ],
      "testing": "Monthly restore validation"
    },
    "communication": {
      "internal": "Slack #incidents",
      "external": "Status page + Twitter",
      "stakeholders": [
        "CEO",
        "CTO",
        "Security",
        "Legal",
        "Customers"
      ],
      "frequency": "Every 30 minutes during incident"
    }
  }
}